uniparser_eastern_armenian/__init__.py
uniparser_eastern_armenian/data/__init__.py
uniparser_eastern_armenian/data/armenian_disambiguation.cg3
uniparser_eastern_armenian/data/bad_analyses.txt
uniparser_eastern_armenian/data/lex_rules.txt
uniparser_eastern_armenian/data/lexemes.txt
uniparser_eastern_armenian/data/paradigms.txt
uniparser_eastern_armenian-2.1.2.dist-info/LICENSE
uniparser_eastern_armenian-2.1.2.dist-info/METADATA
uniparser_eastern_armenian-2.1.2.dist-info/WHEEL
uniparser_eastern_armenian-2.1.2.dist-info/top_level.txt
uniparser_eastern_armenian-2.1.2.dist-info/RECORD
