Metadata-Version: 2.1
Name: uniparser-eastern-armenian
Version: 2.1.2
Summary: Rule-based morphological analysis for Eastern Armenian
Home-page: https://github.com/timarkh/uniparser-grammar-eastern-armenian
Author: Timofey Arkhangelskiy <timarkh@gmail.com>, Alexei Fedorenko, Victoria Khurshudyan, Alexey Polyakov
Author-email: timarkh@gmail.com
License: UNKNOWN
Project-URL: Bug Tracker, https://github.com/timarkh/uniparser-grammar-eastern-armenian/issues
Platform: UNKNOWN
Classifier: Programming Language :: Python :: 3
Classifier: License :: OSI Approved :: MIT License
Classifier: Operating System :: OS Independent
Classifier: Intended Audience :: Science/Research
Classifier: Topic :: Text Processing :: Linguistic
Requires-Python: >=3.7
License-File: LICENSE
Requires-Dist: uniparser-morph (>=2.2.0)
Requires-Dist: importlib-resources
